.gitignore
CHANGES.rst
LICENSE.txt
MANIFEST.in
README.rst
setup.py
src/papavisor/__init__.py
src/papavisor/aioxmlrpc_client.py
src/papavisor.egg-info/PKG-INFO
src/papavisor.egg-info/SOURCES.txt
src/papavisor.egg-info/dependency_links.txt
src/papavisor.egg-info/not-zip-safe
src/papavisor.egg-info/requires.txt
src/papavisor.egg-info/top_level.txt
src/papavisor/config/00_defaults.json
src/papavisor/config/01_template.json
src/papavisor/config/apapavisor.sh
src/papavisor/scripts/apapavisor
src/papavisor/scripts/papavisor