Metadata-Version: 1.1
Name: papavisor
Version: 0.1.0
Summary: papavisor package.
Home-page: https://github.com/webmeisterei/papavisor
Author: Rene Jochum
Author-email: rene@webmeisterei.com
License: MIT
Keywords: papavisor supervisor supervisord
Platform: any
Classifier: Development Status :: 3 - Alpha
Classifier: Intended Audience :: System Administrators
Classifier: License :: OSI Approved :: MIT License
Classifier: Programming Language :: Python :: 3 :: Only
Classifier: Programming Language :: Python :: 3.4
Classifier: Programming Language :: Python :: 3.5
Classifier: Natural Language :: English
Classifier: Operating System :: POSIX
Classifier: Topic :: System :: Boot
Classifier: Topic :: System :: Monitoring
Classifier: Topic :: System :: Systems Administration
